hyperscan/__init__.py
hyperscan/__init__.pyi
hyperscan/_hs_ext.pypy310-pp73-x86_64-linux-gnu.so
hyperscan/_version.py
hyperscan/extension.c
hyperscan/py.typed
hyperscan-0.8.0.dist-info/METADATA
hyperscan-0.8.0.dist-info/WHEEL
hyperscan-0.8.0.dist-info/RECORD
hyperscan-0.8.0.dist-info/licenses/LICENSE
