Metadata-Version: 2.2
Name: hyperscan
Version: 0.8.0
Summary: Python bindings for Hyperscan.
Keywords: regex,hypercan
Author-Email: David Gidwani <david.gidwani@atomweight.io>
License: MIT
Classifier: Development Status :: 4 - Beta
Classifier: Topic :: Software Development :: Libraries
Classifier: Topic :: Software Development :: Libraries :: Python Modules
Classifier: Topic :: Utilities
Classifier: Programming Language :: Python
Classifier: Programming Language :: Python :: 3
Classifier: Programming Language :: Python :: 3.8
Classifier: Programming Language :: Python :: 3.9
Classifier: Programming Language :: Python :: 3.10
Classifier: Programming Language :: Python :: 3.11
Classifier: Programming Language :: Python :: 3.12
Classifier: Programming Language :: Python :: 3.13
Classifier: Programming Language :: Python :: 3.14
Classifier: Programming Language :: Python :: Implementation :: CPython
Classifier: Environment :: Console
Classifier: Intended Audience :: Developers
Classifier: License :: OSI Approved :: MIT License
Classifier: Operating System :: POSIX :: Linux
Classifier: Operating System :: Unix
Classifier: Operating System :: MacOS
Classifier: Operating System :: Microsoft :: Windows
Project-URL: Homepage, https://github.com/darvid/python-hyperscan
Project-URL: Repository, https://github.com/darvid/python-hyperscan
Project-URL: Documentation, https://python-hyperscan.readthedocs.io/en/latest/
Requires-Python: <4.0,>=3.9
